Metadata-Version: 2.1
Name: modbus-crc
Version: 1.3
Summary: CRC-16 calculation for Modbus protocol
Home-page: https://github.com/webtoucher/modbus-crc
Author: Alexey Kuznetsov
Author-email: mirakuru@webtoucher.ru
License: BSD-3-Clause
Classifier: Development Status :: 5 - Production/Stable
Classifier: Intended Audience :: Developers
Classifier: Topic :: Software Development :: Libraries
Classifier: License :: OSI Approved :: BSD License
Classifier: Programming Language :: Python :: 3
Classifier: Operating System :: Microsoft :: Windows
Classifier: Operating System :: POSIX
Classifier: Operating System :: Unix
Classifier: Operating System :: MacOS
License-File: LICENSE.md
